lion_anthropic/__init__.py
lion_anthropic/anthropic_model.py
lion_anthropic/anthropic_service.py
lion_anthropic/api_endpoints/__init__.py
lion_anthropic/api_endpoints/api_request.py
lion_anthropic/api_endpoints/data_models.py
lion_anthropic/api_endpoints/match_data_model.py
lion_anthropic/api_endpoints/match_response.py
lion_anthropic/api_endpoints/models.py
lion_anthropic/api_endpoints/messages/__init__.py
lion_anthropic/api_endpoints/messages/message.py
lion_anthropic/api_endpoints/messages/request_body.py
lion_anthropic/api_endpoints/messages/response_body.py
lion_anthropic/api_endpoints/messages/system.py
lion_anthropic/api_endpoints/messages/contents/__init__.py
lion_anthropic/api_endpoints/messages/contents/base_content.py
lion_anthropic/api_endpoints/messages/contents/document.py
lion_anthropic/api_endpoints/messages/contents/image.py
lion_anthropic/api_endpoints/messages/contents/tool_result.py
lion_anthropic/api_endpoints/messages/contents/tool_use.py
lion_anthropic/api_endpoints/messages/contents/types.py
lion_anthropic/api_endpoints/messages/responses/__init__.py
lion_anthropic/api_endpoints/messages/responses/content.py
lion_anthropic/api_endpoints/messages/responses/delta.py
lion_anthropic/api_endpoints/messages/responses/events.py
lion_anthropic/api_endpoints/messages/responses/stream_events.py
lion_anthropic/api_endpoints/messages/responses/types.py
lion_anthropic/api_endpoints/messages/responses/usage.py
lion_anthropic/api_endpoints/messages/tools/__init__.py
lion_anthropic/api_endpoints/messages/tools/base.py
lion_anthropic/api_endpoints/messages/tools/bash.py
lion_anthropic/api_endpoints/messages/tools/computer_use.py
lion_anthropic/api_endpoints/messages/tools/custom.py
lion_anthropic/api_endpoints/messages/tools/text_editor.py
lion_anthropic/api_endpoints/messages/tools/tool_choice.py
lion_anthropic/api_endpoints/messages/tools/tool_input_schema.py
lion_anthropic-0.1.0.dist-info/LICENSE
lion_anthropic-0.1.0.dist-info/METADATA
lion_anthropic-0.1.0.dist-info/WHEEL
lion_anthropic-0.1.0.dist-info/top_level.txt
lion_anthropic-0.1.0.dist-info/RECORD
